sphinx_codefence.py
sphinx_codefence-0.1.0.dist-info/METADATA
sphinx_codefence-0.1.0.dist-info/WHEEL
sphinx_codefence-0.1.0.dist-info/top_level.txt
sphinx_codefence-0.1.0.dist-info/RECORD
